opentariff/Enums/base_enums.py
opentariff/Enums/product_enums.py
opentariff/Enums/tariff_enums.py
opentariff/__init__.py
opentariff/models/product_models.py
opentariff/models/tariff_models.py
opentariff-1.1.0.dist-info/LICENSE
opentariff-1.1.0.dist-info/METADATA
opentariff-1.1.0.dist-info/WHEEL
opentariff-1.1.0.dist-info/RECORD
