Metadata-Version: 2.3
Name: OpenTariff
Version: 1.1.0
Summary: An open-source tariff schema definition
Author: Future Energy Associates
Author-email: hello@futureenergy.associates
Requires-Python: >=3.10,<4.0
Classifier: Programming Language :: Python :: 3
Classifier: Programming Language :: Python :: 3.10
Classifier: Programming Language :: Python :: 3.11
Classifier: Programming Language :: Python :: 3.12
Classifier: Programming Language :: Python :: 3.13
Requires-Dist: pydantic (>=2.10.3,<3.0.0)
